llama_index/storage/kvstore/redis/__init__.py
llama_index/storage/kvstore/redis/base.py
llama_index_storage_kvstore_redis-0.4.1.dist-info/METADATA
llama_index_storage_kvstore_redis-0.4.1.dist-info/WHEEL
llama_index_storage_kvstore_redis-0.4.1.dist-info/licenses/LICENSE
llama_index_storage_kvstore_redis-0.4.1.dist-info/RECORD
